higgs_boson.py
builder/Commands.py
builder/DependencyBuildManager.py
builder/Dockerfile.py
builder/HiggsBuilder.py
builder/PeruManager.py
builder/Utils.py
builder/YamlParser.py
higgs_boson-0.1.0.dist-info/DESCRIPTION.rst
higgs_boson-0.1.0.dist-info/METADATA
higgs_boson-0.1.0.dist-info/RECORD
higgs_boson-0.1.0.dist-info/WHEEL
higgs_boson-0.1.0.dist-info/entry_points.txt
higgs_boson-0.1.0.dist-info/metadata.json
higgs_boson-0.1.0.dist-info/top_level.txt
